nonebot_plugin_apex_api_query/__init__.py
nonebot_plugin_apex_api_query/config.py
nonebot_plugin_apex_api_query/data.py
nonebot_plugin_apex_api_query/data_source.py
nonebot_plugin_apex_api_query-25.1.16.dist-info/LICENSE
nonebot_plugin_apex_api_query-25.1.16.dist-info/METADATA
nonebot_plugin_apex_api_query-25.1.16.dist-info/WHEEL
nonebot_plugin_apex_api_query-25.1.16.dist-info/RECORD
