Metadata-Version: 2.3
Name: nonebot-plugin-apex-api-query
Version: 25.1.16
Summary: 
License: MIT
Author: H-xiaoH
Author-email: a412454922@gmail.com
Requires-Python: >=3.9,<4.0
Classifier: License :: OSI Approved :: MIT License
Classifier: Programming Language :: Python :: 3
Classifier: Programming Language :: Python :: 3.9
Classifier: Programming Language :: Python :: 3.10
Classifier: Programming Language :: Python :: 3.11
Classifier: Programming Language :: Python :: 3.12
Classifier: Programming Language :: Python :: 3.13
Requires-Dist: httpx (>=0.28.1)
Requires-Dist: nonebot-adapter-onebot (>=2.4.6)
Requires-Dist: nonebot-plugin-alconna (>=0.54.2)
Requires-Dist: nonebot2 (>=2.4.1)
Project-URL: Bug Tracker, https://github.com/H-xiaoH/nonebot-plugin-apex-api-query/issues
Project-URL: Documentation, https://github.com/H-xiaoH/nonebot-plugin-apex-api-query/blob/main/README.md
Project-URL: Homepage, https://github.com/H-xiaoH/nonebot-plugin-apex-api-query
Project-URL: Repository, https://github.com/H-xiaoH/nonebot-plugin-apex-api-query
